rltools/__init__.py
rltools/external/rl_tools/include/rl_tools/rl_tools.h
rltools/external/rl_tools/include/rl_tools/universe.h
rltools/external/rl_tools/include/rl_tools/version.h
rltools/external/rl_tools/include/rl_tools/containers/matrix/matrix.h
rltools/external/rl_tools/include/rl_tools/containers/matrix/operations_arm.h
rltools/external/rl_tools/include/rl_tools/containers/matrix/operations_cpu.h
rltools/external/rl_tools/include/rl_tools/containers/matrix/operations_cpu_accelerate.h
rltools/external/rl_tools/include/rl_tools/containers/matrix/operations_cpu_blas.h
rltools/external/rl_tools/include/rl_tools/containers/matrix/operations_cpu_mkl.h
rltools/external/rl_tools/include/rl_tools/containers/matrix/operations_cpu_openblas.h
rltools/external/rl_tools/include/rl_tools/containers/matrix/operations_cuda.h
rltools/external/rl_tools/include/rl_tools/containers/matrix/operations_dummy.h
rltools/external/rl_tools/include/rl_tools/containers/matrix/operations_esp32.h
rltools/external/rl_tools/include/rl_tools/containers/matrix/operations_generic.h
rltools/external/rl_tools/include/rl_tools/containers/matrix/operations_wasm32.h
rltools/external/rl_tools/include/rl_tools/containers/matrix/persist_code.h
rltools/external/rl_tools/include/rl_tools/containers/matrix/persist_hdf5.h
rltools/external/rl_tools/include/rl_tools/containers/tensor/operations_arm.h
rltools/external/rl_tools/include/rl_tools/containers/tensor/operations_cpu.h
rltools/external/rl_tools/include/rl_tools/containers/tensor/operations_cpu_accelerate.h
rltools/external/rl_tools/include/rl_tools/containers/tensor/operations_cpu_blas.h
rltools/external/rl_tools/include/rl_tools/containers/tensor/operations_cpu_mkl.h
rltools/external/rl_tools/include/rl_tools/containers/tensor/operations_cpu_openblas.h
rltools/external/rl_tools/include/rl_tools/containers/tensor/operations_cuda.h
rltools/external/rl_tools/include/rl_tools/containers/tensor/operations_generic.h
rltools-2.2.1.dist-info/METADATA
rltools-2.2.1.dist-info/WHEEL
rltools-2.2.1.dist-info/licenses/LICENSE
rltools-2.2.1.dist-info/RECORD
