Metadata-Version: 2.4
Name: rltools
Version: 2.2.1
Summary: A Python wrapper for RLtools
Project-URL: Homepage, https://github.com/rl-tools/python-interface
Project-URL: Issues, https://github.com/rl-tools/python-interface/issues
Author-email: Jonas Eschmann <jonas.eschmann@gmail.com>
License-File: LICENSE
Classifier: License :: OSI Approved :: MIT License
Classifier: Operating System :: OS Independent
Classifier: Programming Language :: Python :: 3
Requires-Python: >=3.8
Requires-Dist: pybind11
Provides-Extra: learning-curves
Requires-Dist: gymnasium[mujoco]==0.29.1; extra == 'learning-curves'
Requires-Dist: stable-baselines3==2.3.0; extra == 'learning-curves'
Requires-Dist: torch==2.2.1; extra == 'learning-curves'
Provides-Extra: mkl
Requires-Dist: mkl; extra == 'mkl'
Requires-Dist: mkl-include; extra == 'mkl'
Provides-Extra: onnx
Requires-Dist: onnx; extra == 'onnx'
Provides-Extra: tests
Requires-Dist: onnx; extra == 'tests'
Requires-Dist: torch; extra == 'tests'
